api_key_detector/.git
api_key_detector/.gitignore
api_key_detector/LICENSE
api_key_detector/README.md
api_key_detector/__init__.py
api_key_detector/__main__.py
api_key_detector/charset.py
api_key_detector/classifier_singleton.py
api_key_detector/classifiers_test.py
api_key_detector/config.py
api_key_detector/config.yml
api_key_detector/dataset_plotter.py
api_key_detector/default_conf.json
api_key_detector/detector.py
api_key_detector/detector_config.py
api_key_detector/entropy.py
api_key_detector/log_config.json
api_key_detector/neuralnets_test.py
api_key_detector/requirements.txt
api_key_detector/sequentiality.py
api_key_detector/string_classifier.pki
api_key_detector/string_classifier.py
api_key_detector/strings_filter.py
api_key_detector/strings_filter_singleton.py
api_key_detector/words_finder.py
api_key_detector/words_finder_singleton.py
api_key_detector/__pycache__/__init__.cpython-313.pyc
api_key_detector/__pycache__/charset.cpython-313.pyc
api_key_detector/__pycache__/classifier_singleton.cpython-313.pyc
api_key_detector/__pycache__/config.cpython-313.pyc
api_key_detector/__pycache__/entropy.cpython-313.pyc
api_key_detector/__pycache__/sequentiality.cpython-313.pyc
api_key_detector/__pycache__/string_classifier.cpython-313.pyc
api_key_detector/datasets/classifier_learnset.npy
api_key_detector/datasets/classifier_testset_extended.npy
api_key_detector/datasets/computer_wordlist.txt
api_key_detector/datasets/english_wordlist.txt
api_key_detector/datasets/esg-key-values3.txt
api_key_detector/datasets/esg-text-values3.txt
api_key_detector/datasets/keys/api_key_generator.py
api_key_detector/datasets/keys/api_test.txt
api_key_detector/datasets/keys/api_test_extended.txt
api_key_detector/datasets/keys/blacklist.txt
api_key_detector/datasets/keys/gen_amazonaws.txt
api_key_detector/datasets/keys/gen_base91.txt
api_key_detector/datasets/keys/gen_beepbooptoken.txt
api_key_detector/datasets/keys/gen_bitly.txt
api_key_detector/datasets/keys/gen_facebookappsecret.txt
ak_keydetector-0.0.3.dist-info/LICENSE
ak_keydetector-0.0.3.dist-info/METADATA
ak_keydetector-0.0.3.dist-info/WHEEL
ak_keydetector-0.0.3.dist-info/top_level.txt
ak_keydetector-0.0.3.dist-info/RECORD
