Metadata-Version: 2.2
Name: ak-keydetector
Version: 0.0.3
Summary: ML Based API Key Detector
Home-page: https://github.com/appknox/ml-key-detector
Author: Appknox Engineering
Author-email: engineering@appknox.com
License: Apache-2.0 license
Requires-Python: >=3.8
License-File: LICENSE
Requires-Dist: matplotlib==3.10.0
Requires-Dist: numpy==1.26.4
Requires-Dist: plotly==5.13.0
Requires-Dist: PyYAML>=5.4.1
Requires-Dist: rstr==3.2.0
Requires-Dist: scikit-learn==1.6.1
Requires-Dist: scipy==1.15.1
Dynamic: author
Dynamic: author-email
Dynamic: description
Dynamic: description-content-type
Dynamic: home-page
Dynamic: license
Dynamic: requires-dist
Dynamic: requires-python
Dynamic: summary
